mtbmasker/__init__.py
mtbmasker/cli.py
mtbmasker/masker.py
mtbmasker/utils.py
mtbmasker-0.1.2.dist-info/METADATA
mtbmasker-0.1.2.dist-info/WHEEL
mtbmasker-0.1.2.dist-info/entry_points.txt
mtbmasker-0.1.2.dist-info/top_level.txt
mtbmasker-0.1.2.dist-info/RECORD
