Metadata-Version: 2.4
Name: mtbmasker
Version: 0.1.2
Summary: Generate isolate-specific genome masks for Mycobacterium tuberculosis
Author-email: Etienne Ntumba Kabongo <etienne.ntumba.kabongo@umontreal.ca>, Dan Whiley <dan.whiley@ntu.ac.uk>
License-Expression: MIT
Requires-Python: >=3.8
Requires-Dist: typer>=0.9.0
